{
    "sezon": [
        "2022-2023"
    ],
    "hafta": [
        "22"
    ],
    "takimlar": {
        "takim_1": {
            "takimAdi": [
                "GAZİANTEP FUTBOL KULÜBÜ A.Ş."
            ],
            "skor": [
                "4"
            ],
            "ilk11": [
                {
                    "oyuncuAdi": "GÜNAY GÜVENÇ",
                    "formaNo": "1"
                },
                {
                    "oyuncuAdi": "ALEXANDRU IULIAN MAXIM",
                    "formaNo": "44"
                },
                {
                    "oyuncuAdi": "EL HADJI PAPY MISON DJILOBODJI",
                    "formaNo": "3"
                },
                {
                    "oyuncuAdi": "ERTUĞRUL ERSOY",
                    "formaNo": "15"
                },
                {
                    "oyuncuAdi": "FURKAN SOYALP",
                    "formaNo": "5"
                },
                {
                    "oyuncuAdi": "HALİL İBRAHİM PEHLİVAN",
                    "formaNo": "11"
                },
                {
                    "oyuncuAdi": "JOAO VITOR BRANDAO FIGUEIREDO",
                    "formaNo": "25"
                },
                {
                    "oyuncuAdi": "LAZAR MARKOVIC",
                    "formaNo": "50"
                },
                {
                    "oyuncuAdi": "MARKO JEVTOVIC",
                    "formaNo": "8"
                },
                {
                    "oyuncuAdi": "MUSTAFA ESKİHELLAÇ",
                    "formaNo": "17"
                },
                {
                    "oyuncuAdi": "ÖMÜRCAN ARTAN",
                    "formaNo": "27"
                }
            ],
            "yedekler": [
                {
                    "oyuncuAdi": "MUSTAFA BURAK BOZAN",
                    "formaNo": "71"
                },
                {
                    "oyuncuAdi": "ABDULKERİM  ÇAKAR",
                    "formaNo": "23"
                },
                {
                    "oyuncuAdi": "ALEXANDER MERKEL",
                    "formaNo": "52"
                },
                {
                    "oyuncuAdi": "ARDA KIZILDAĞ",
                    "formaNo": "4"
                },
                {
                    "oyuncuAdi": "BERKAN KÜPELİKILINÇ",
                    "formaNo": "2"
                },
                {
                    "oyuncuAdi": "LUKA STANKOVSKI",
                    "formaNo": "80"
                },
                {
                    "oyuncuAdi": "MATEJ  HANOUSEK",
                    "formaNo": "16"
                },
                {
                    "oyuncuAdi": "MİRZA CİHAN",
                    "formaNo": "26"
                },
                {
                    "oyuncuAdi": "ONURHAN BABUŞCU",
                    "formaNo": "30"
                },
                {
                    "oyuncuAdi": "VALMIR VELIU",
                    "formaNo": "7"
                }
            ],
            "teknikSorumlu": [
                ""
            ],
            "kartlar": [
                {
                    "oyuncu": "FURKAN SOYALP",
                    "kartTuru": "Sarı Kart",
                    "dakika": "71.dk"
                },
                {
                    "oyuncu": "ÖMÜRCAN ARTAN",
                    "kartTuru": "Sarı Kart",
                    "dakika": "87.dk"
                },
                {
                    "oyuncu": "EL HADJI PAPY MISON DJILOBODJI",
                    "kartTuru": "Sarı Kart",
                    "dakika": "35.dk"
                },
                {
                    "oyuncu": "LUKA STANKOVSKI",
                    "kartTuru": "Sarı Kart",
                    "dakika": "90+6.dk"
                }
            ],
            "oyundanCikanlar": [
                {
                    "oyuncu": "MUSTAFA ESKİHELLAÇ",
                    "dakika": "53.dk"
                },
                {
                    "oyuncu": "FURKAN SOYALP",
                    "dakika": "81.dk"
                },
                {
                    "oyuncu": "LAZAR MARKOVIC",
                    "dakika": "81.dk"
                },
                {
                    "oyuncu": "ALEXANDRU IULIAN MAXIM",
                    "dakika": "90+3.dk"
                }
            ],
            "oyunaGirenler": [
                {
                    "oyuncu": "VALMIR VELIU",
                    "dakika": "53.dk"
                },
                {
                    "oyuncu": "ALEXANDER MERKEL",
                    "dakika": "81.dk"
                },
                {
                    "oyuncu": "MİRZA CİHAN",
                    "dakika": "81.dk"
                },
                {
                    "oyuncu": "LUKA STANKOVSKI",
                    "dakika": "90+3.dk"
                }
            ],
            "goller": [
                {
                    "oyuncu": "MARKO JEVTOVIC",
                    "dakika": "38.dk",
                    "golTipi": "F"
                },
                {
                    "oyuncu": "LAZAR MARKOVIC",
                    "dakika": "56.dk",
                    "golTipi": "H"
                },
                {
                    "oyuncu": "LAZAR MARKOVIC",
                    "dakika": "77.dk",
                    "golTipi": "F"
                },
                {
                    "oyuncu": "ALEXANDER MERKEL",
                    "dakika": "88.dk",
                    "golTipi": "F"
                }
            ]
        },
        "takim_2": {
            "takimAdi": [
                "ATAKAŞ HATAYSPOR"
            ],
            "skor": [
                "1"
            ],
            "ilk11": [
                {
                    "oyuncuAdi": "ERCE KARDEŞLER",
                    "formaNo": "1"
                },
                {
                    "oyuncuAdi": "KAMİL AHMET ÇÖREKÇİ",
                    "formaNo": "12"
                },
                {
                    "oyuncuAdi": "BURAK BEKAROĞLU",
                    "formaNo": "86"
                },
                {
                    "oyuncuAdi": "RECEP BURAK YILMAZ",
                    "formaNo": "15"
                },
                {
                    "oyuncuAdi": "SAMUEL AYOMIDE ADEKUGBE",
                    "formaNo": "23"
                },
                {
                    "oyuncuAdi": "MUSA ÇAĞIRAN",
                    "formaNo": "6"
                },
                {
                    "oyuncuAdi": "RUBEN TIAGO RODRIGUES RIBEIRO",
                    "formaNo": "7"
                },
                {
                    "oyuncuAdi": "MEHDİ BOUDJEMAA",
                    "formaNo": "8"
                },
                {
                    "oyuncuAdi": "SABA LOBJANIDZE",
                    "formaNo": "11"
                },
                {
                    "oyuncuAdi": "AYOUB EL KAABİ",
                    "formaNo": "25"
                },
                {
                    "oyuncuAdi": "BERTUĞ ÖZGÜR YILDIRIM",
                    "formaNo": "99"
                }
            ],
            "yedekler": [
                {
                    "oyuncuAdi": "ABDULLAH YİĞİTER",
                    "formaNo": "31"
                },
                {
                    "oyuncuAdi": "ENGİN CAN AKSOY",
                    "formaNo": "57"
                },
                {
                    "oyuncuAdi": "KERİM ALICI",
                    "formaNo": "22"
                },
                {
                    "oyuncuAdi": "KAAN KANAK",
                    "formaNo": "26"
                },
                {
                    "oyuncuAdi": "ONUR ERGÜN",
                    "formaNo": "4"
                },
                {
                    "oyuncuAdi": "AABID RAYANE",
                    "formaNo": "10"
                },
                {
                    "oyuncuAdi": "SADIK BAŞ",
                    "formaNo": "77"
                },
                {
                    "oyuncuAdi": "CHRISTIAN ATSU TWASAM",
                    "formaNo": "30"
                },
                {
                    "oyuncuAdi": "JOSE LUIS  MENDES DE ANDRADE",
                    "formaNo": "29"
                },
                {
                    "oyuncuAdi": "JEREMY CALVIN  DUDZİAK",
                    "formaNo": "71"
                }
            ],
            "teknikSorumlu": [
                ""
            ],
            "kartlar": [
                {
                    "oyuncu": "KAAN KANAK",
                    "kartTuru": "Sarı Kart",
                    "dakika": "79.dk"
                },
                {
                    "oyuncu": "ERCE KARDEŞLER",
                    "kartTuru": "Sarı Kart",
                    "dakika": "90+7.dk"
                }
            ],
            "oyundanCikanlar": [
                {
                    "oyuncu": "MUSA ÇAĞIRAN",
                    "dakika": "81.dk"
                },
                {
                    "oyuncu": "SABA LOBJANIDZE",
                    "dakika": "60.dk"
                },
                {
                    "oyuncu": "RUBEN TIAGO RODRIGUES RIBEIRO",
                    "dakika": "60.dk"
                },
                {
                    "oyuncu": "MEHDİ BOUDJEMAA",
                    "dakika": "60.dk"
                },
                {
                    "oyuncu": "SAMUEL AYOMIDE ADEKUGBE",
                    "dakika": "60.dk"
                }
            ],
            "oyunaGirenler": [
                {
                    "oyuncu": "ONUR ERGÜN",
                    "dakika": "81.dk"
                },
                {
                    "oyuncu": "JOSE LUIS  MENDES DE ANDRADE",
                    "dakika": "60.dk"
                },
                {
                    "oyuncu": "KAAN KANAK",
                    "dakika": "60.dk"
                },
                {
                    "oyuncu": "AABID RAYANE",
                    "dakika": "60.dk"
                },
                {
                    "oyuncu": "JEREMY CALVIN  DUDZİAK",
                    "dakika": "60.dk"
                }
            ],
            "goller": [
                {
                    "oyuncu": "AYOUB EL KAABİ",
                    "dakika": "27.dk",
                    "golTipi": "F"
                }
            ]
        }
    }
}