{
    "sezon": [
        "2021-2022"
    ],
    "hafta": [
        "14"
    ],
    "takimlar": {
        "takim_1": {
            "takimAdi": [
                "FRAPORT TAV ANTALYASPOR"
            ],
            "skor": [
                "3"
            ],
            "ilk11": [
                {
                    "oyuncuAdi": "RUUD JORGE BOFFIN",
                    "formaNo": "25"
                },
                {
                    "oyuncuAdi": "EDINALDO GOMES PEREIRA",
                    "formaNo": "4"
                },
                {
                    "oyuncuAdi": "DOĞUKAN SİNİK",
                    "formaNo": "7"
                },
                {
                    "oyuncuAdi": "GÜRAY VURAL",
                    "formaNo": "11"
                },
                {
                    "oyuncuAdi": "PAUL OMO MUKAIRU",
                    "formaNo": "12"
                },
                {
                    "oyuncuAdi": "FEDOR KUDRIASHOV",
                    "formaNo": "13"
                },
                {
                    "oyuncuAdi": "ANDREA POLI",
                    "formaNo": "15"
                },
                {
                    "oyuncuAdi": "ALFREDO KULEMBE RIBEIRO",
                    "formaNo": "16"
                },
                {
                    "oyuncuAdi": "AMILTON MINERVINO DA SILVA",
                    "formaNo": "23"
                },
                {
                    "oyuncuAdi": "BÜNYAMİN BALCI",
                    "formaNo": "77"
                },
                {
                    "oyuncuAdi": "VEYSEL SARI",
                    "formaNo": "89"
                }
            ],
            "yedekler": [
                {
                    "oyuncuAdi": "DOĞUKAN ÖZKAN",
                    "formaNo": "1"
                },
                {
                    "oyuncuAdi": "SHEREL CONSTANCİO FLORANUS",
                    "formaNo": "2"
                },
                {
                    "oyuncuAdi": "BAHADIR ÖZTÜRK",
                    "formaNo": "5"
                },
                {
                    "oyuncuAdi": "EREN ALBAYRAK",
                    "formaNo": "6"
                },
                {
                    "oyuncuAdi": "NURİ ŞAHİN",
                    "formaNo": "8"
                },
                {
                    "oyuncuAdi": "DENI MILOSEVIC",
                    "formaNo": "10"
                },
                {
                    "oyuncuAdi": "ERSİN ZEHİR",
                    "formaNo": "18"
                },
                {
                    "oyuncuAdi": "HOUSSAM EDDINE GHACHA",
                    "formaNo": "27"
                },
                {
                    "oyuncuAdi": "GÖKDENİZ BAYRAKDAR",
                    "formaNo": "41"
                },
                {
                    "oyuncuAdi": "HAKAN ÖZMERT",
                    "formaNo": "88"
                }
            ],
            "teknikSorumlu": [
                "ALFONS FRANCISCUS GROENENDIJK"
            ],
            "kartlar": [
                {
                    "oyuncu": "AMILTON MINERVINO DA SILVA",
                    "kartTuru": "Sarı Kart",
                    "dakika": "54.dk"
                }
            ],
            "oyundanCikanlar": [
                {
                    "oyuncu": "ALFREDO KULEMBE RIBEIRO",
                    "dakika": "85.dk"
                },
                {
                    "oyuncu": "AMILTON MINERVINO DA SILVA",
                    "dakika": "85.dk"
                },
                {
                    "oyuncu": "FEDOR KUDRIASHOV",
                    "dakika": "85.dk"
                },
                {
                    "oyuncu": "PAUL OMO MUKAIRU",
                    "dakika": "90.dk"
                },
                {
                    "oyuncu": "ANDREA POLI",
                    "dakika": "71.dk"
                }
            ],
            "oyunaGirenler": [
                {
                    "oyuncu": "SHEREL CONSTANCİO FLORANUS",
                    "dakika": "85.dk"
                },
                {
                    "oyuncu": "DENI MILOSEVIC",
                    "dakika": "85.dk"
                },
                {
                    "oyuncu": "HAKAN ÖZMERT",
                    "dakika": "71.dk"
                },
                {
                    "oyuncu": "GÖKDENİZ BAYRAKDAR",
                    "dakika": "90.dk"
                },
                {
                    "oyuncu": "BAHADIR ÖZTÜRK",
                    "dakika": "85.dk"
                }
            ],
            "goller": [
                {
                    "oyuncu": "BÜNYAMİN BALCI",
                    "dakika": "40.dk",
                    "golTipi": "F"
                },
                {
                    "oyuncu": "PAUL OMO MUKAIRU",
                    "dakika": "68.dk",
                    "golTipi": "F"
                },
                {
                    "oyuncu": "SHEREL CONSTANCİO FLORANUS",
                    "dakika": "90.dk",
                    "golTipi": "F"
                }
            ]
        },
        "takim_2": {
            "takimAdi": [
                "AYTEMİZ ALANYASPOR"
            ],
            "skor": [
                "0"
            ],
            "ilk11": [
                {
                    "oyuncuAdi": "JOSE CARLOS COENTRAO MARAFONA",
                    "formaNo": "28"
                },
                {
                    "oyuncuAdi": "ELHADJI BABACAR KHOUMA",
                    "formaNo": "10"
                },
                {
                    "oyuncuAdi": "EFKAN BEKİROĞLU",
                    "formaNo": "11"
                },
                {
                    "oyuncuAdi": "CHIDOZIE COLLINS AWAZIEM",
                    "formaNo": "15"
                },
                {
                    "oyuncuAdi": "FATİH AKSOY",
                    "formaNo": "20"
                },
                {
                    "oyuncuAdi": "DANIEL JOAO SANTOS CANDEIAS",
                    "formaNo": "21"
                },
                {
                    "oyuncuAdi": "EMRE AKBABA",
                    "formaNo": "23"
                },
                {
                    "oyuncuAdi": "JUAN FRANCISCO MORENO FUERTES",
                    "formaNo": "24"
                },
                {
                    "oyuncuAdi": "MIHA MEVLJA",
                    "formaNo": "25"
                },
                {
                    "oyuncuAdi": "TAYFUR BİNGÖL",
                    "formaNo": "75"
                },
                {
                    "oyuncuAdi": "DAVIDSON DA LUZ PEREIRA",
                    "formaNo": "91"
                }
            ],
            "yedekler": [
                {
                    "oyuncuAdi": "YUSUF KARAGÖZ",
                    "formaNo": "30"
                },
                {
                    "oyuncuAdi": "BULUTHAN BULUT",
                    "formaNo": "5"
                },
                {
                    "oyuncuAdi": "UMUT GÜNEŞ",
                    "formaNo": "6"
                },
                {
                    "oyuncuAdi": "EFECAN KARACA",
                    "formaNo": "7"
                },
                {
                    "oyuncuAdi": "AHMED ILDIZ",
                    "formaNo": "8"
                },
                {
                    "oyuncuAdi": "FAMARA DIEDHIOU",
                    "formaNo": "14"
                },
                {
                    "oyuncuAdi": "WILSON BRUNO NAVAL DA COSTA ABREU EDUARDO",
                    "formaNo": "17"
                },
                {
                    "oyuncuAdi": "NEMANJA MILUNOVIC",
                    "formaNo": "19"
                },
                {
                    "oyuncuAdi": "CRISTIAN ALEXIS BORJA GONZALEZ",
                    "formaNo": "31"
                },
                {
                    "oyuncuAdi": "FURKAN BAYIR",
                    "formaNo": "35"
                }
            ],
            "teknikSorumlu": [
                "BÜLENT KORKMAZ"
            ],
            "kartlar": [
                {
                    "oyuncu": "TAYFUR BİNGÖL",
                    "kartTuru": "Çift Sarı Kart",
                    "dakika": "65.dk"
                },
                {
                    "oyuncu": "CHIDOZIE COLLINS AWAZIEM",
                    "kartTuru": "Sarı Kart",
                    "dakika": "36.dk"
                }
            ],
            "oyundanCikanlar": [
                {
                    "oyuncu": "DANIEL JOAO SANTOS CANDEIAS",
                    "dakika": "57.dk"
                },
                {
                    "oyuncu": "JUAN FRANCISCO MORENO FUERTES",
                    "dakika": "46.dk"
                },
                {
                    "oyuncu": "EFKAN BEKİROĞLU",
                    "dakika": "57.dk"
                },
                {
                    "oyuncu": "DAVIDSON DA LUZ PEREIRA",
                    "dakika": "70.dk"
                },
                {
                    "oyuncu": "ELHADJI BABACAR KHOUMA",
                    "dakika": "70.dk"
                }
            ],
            "oyunaGirenler": [
                {
                    "oyuncu": "WILSON BRUNO NAVAL DA COSTA ABREU EDUARDO",
                    "dakika": "57.dk"
                },
                {
                    "oyuncu": "CRISTIAN ALEXIS BORJA GONZALEZ",
                    "dakika": "46.dk"
                },
                {
                    "oyuncu": "EFECAN KARACA",
                    "dakika": "57.dk"
                },
                {
                    "oyuncu": "AHMED ILDIZ",
                    "dakika": "70.dk"
                },
                {
                    "oyuncu": "FAMARA DIEDHIOU",
                    "dakika": "70.dk"
                }
            ],
            "goller": []
        }
    }
}