{
    "sezon": [
        "2015-2016"
    ],
    "hafta": [
        "9"
    ],
    "takimlar": {
        "takim_1": {
            "takimAdi": [
                "ÇAYKUR RİZESPOR A.Ş."
            ],
            "skor": [
                "0"
            ],
            "ilk11": [
                {
                    "oyuncuAdi": "CHARLES HUBERT ITANDJE",
                    "formaNo": "1"
                },
                {
                    "oyuncuAdi": "AHMET İLHAN ÖZEK",
                    "formaNo": "78"
                },
                {
                    "oyuncuAdi": "DENİZ KADAH",
                    "formaNo": "63"
                },
                {
                    "oyuncuAdi": "SERCAN KAYA",
                    "formaNo": "7"
                },
                {
                    "oyuncuAdi": "LEONY LEONARD KWEUKE",
                    "formaNo": "9"
                },
                {
                    "oyuncuAdi": "MURAT DURUER",
                    "formaNo": "21"
                },
                {
                    "oyuncuAdi": "CEDRICK MAKIADI",
                    "formaNo": "16"
                },
                {
                    "oyuncuAdi": "EREN ALBAYRAK",
                    "formaNo": "11"
                },
                {
                    "oyuncuAdi": "GODFREYITAMA OBOABONA",
                    "formaNo": "2"
                },
                {
                    "oyuncuAdi": "OUSMANE VIERA DIARRASSOUBA",
                    "formaNo": "3"
                },
                {
                    "oyuncuAdi": "KORAY ALTINAY",
                    "formaNo": "4"
                }
            ],
            "yedekler": [
                {
                    "oyuncuAdi": "GÖKHAN AKKAN",
                    "formaNo": "23"
                },
                {
                    "oyuncuAdi": "MEHMET AKYÜZ",
                    "formaNo": "17"
                },
                {
                    "oyuncuAdi": "ROBIN YALÇIN",
                    "formaNo": "6"
                },
                {
                    "oyuncuAdi": "DHURGHAM ISMAEL DAWOOD AL-QURAISHI",
                    "formaNo": "53"
                },
                {
                    "oyuncuAdi": "LUDOVIC SYLVESTRE",
                    "formaNo": "14"
                },
                {
                    "oyuncuAdi": "PATRYK TUSZYNSKI",
                    "formaNo": "8"
                },
                {
                    "oyuncuAdi": "ÜMİT KORKMAZ",
                    "formaNo": "55"
                }
            ],
            "teknikSorumlu": [
                "HİKMET KARAMAN"
            ],
            "kartlar": [
                {
                    "oyuncu": "KORAY ALTINAY",
                    "kartTuru": "Sarı Kart",
                    "dakika": "54.dk"
                },
                {
                    "oyuncu": "DHURGHAM ISMAEL DAWOOD AL-QURAISHI",
                    "kartTuru": "Sarı Kart",
                    "dakika": "65.dk"
                }
            ],
            "oyundanCikanlar": [
                {
                    "oyuncu": "SERCAN KAYA",
                    "dakika": "62.dk"
                },
                {
                    "oyuncu": "AHMET İLHAN ÖZEK",
                    "dakika": "46.dk"
                },
                {
                    "oyuncu": "MURAT DURUER",
                    "dakika": "62.dk"
                }
            ],
            "oyunaGirenler": [
                {
                    "oyuncu": "DHURGHAM ISMAEL DAWOOD AL-QURAISHI",
                    "dakika": "62.dk"
                },
                {
                    "oyuncu": "LUDOVIC SYLVESTRE",
                    "dakika": "46.dk"
                },
                {
                    "oyuncu": "MEHMET AKYÜZ",
                    "dakika": "62.dk"
                }
            ],
            "goller": []
        },
        "takim_2": {
            "takimAdi": [
                "AKHİSAR BELEDİYE GENÇLİK VE SPOR"
            ],
            "skor": [
                "2"
            ],
            "ilk11": [
                {
                    "oyuncuAdi": "MILAN LUKAC",
                    "formaNo": "1"
                },
                {
                    "oyuncuAdi": "DOUGLAS FERREIRA",
                    "formaNo": "2"
                },
                {
                    "oyuncuAdi": "MERTER YÜCE",
                    "formaNo": "6"
                },
                {
                    "oyuncuAdi": "GÜRAY VURAL",
                    "formaNo": "10"
                },
                {
                    "oyuncuAdi": "LEOCISIO JULIO SAMI",
                    "formaNo": "17"
                },
                {
                    "oyuncuAdi": "AHMET CEBE",
                    "formaNo": "20"
                },
                {
                    "oyuncuAdi": "JOEL LANDRY TSAFACK NGUEMO",
                    "formaNo": "21"
                },
                {
                    "oyuncuAdi": "HUGO RODALLEGA MARTINEZ",
                    "formaNo": "23"
                },
                {
                    "oyuncuAdi": "CUSTODIO MIGUEL DIAS DE CASTRO",
                    "formaNo": "27"
                },
                {
                    "oyuncuAdi": "CANER OSMANPAŞA",
                    "formaNo": "88"
                },
                {
                    "oyuncuAdi": "KADİR KELEŞ",
                    "formaNo": "89"
                }
            ],
            "yedekler": [
                {
                    "oyuncuAdi": "BORA KÖRK",
                    "formaNo": "35"
                },
                {
                    "oyuncuAdi": "İSMAİL KONUK",
                    "formaNo": "4"
                },
                {
                    "oyuncuAdi": "İBRAHİM HALİL ÇOLAK",
                    "formaNo": "7"
                },
                {
                    "oyuncuAdi": "ONUR AYIK",
                    "formaNo": "11"
                },
                {
                    "oyuncuAdi": "AYKUT ÇEVİKER",
                    "formaNo": "18"
                },
                {
                    "oyuncuAdi": "BRUNO FERREIRA MOMBRA ROSA",
                    "formaNo": "80"
                },
                {
                    "oyuncuAdi": "HASAN SALİH KABZE",
                    "formaNo": "99"
                }
            ],
            "teknikSorumlu": [
                "CİHAT ARSLAN"
            ],
            "kartlar": [
                {
                    "oyuncu": "MERTER YÜCE",
                    "kartTuru": "Sarı Kart",
                    "dakika": "30.dk"
                },
                {
                    "oyuncu": "AHMET CEBE",
                    "kartTuru": "Sarı Kart",
                    "dakika": "65.dk"
                }
            ],
            "oyundanCikanlar": [
                {
                    "oyuncu": "GÜRAY VURAL",
                    "dakika": "78.dk"
                },
                {
                    "oyuncu": "CUSTODIO MIGUEL DIAS DE CASTRO",
                    "dakika": "70.dk"
                },
                {
                    "oyuncu": "LEOCISIO JULIO SAMI",
                    "dakika": "75.dk"
                }
            ],
            "oyunaGirenler": [
                {
                    "oyuncu": "ONUR AYIK",
                    "dakika": "78.dk"
                },
                {
                    "oyuncu": "AYKUT ÇEVİKER",
                    "dakika": "70.dk"
                },
                {
                    "oyuncu": "İBRAHİM HALİL ÇOLAK",
                    "dakika": "75.dk"
                }
            ],
            "goller": [
                {
                    "oyuncu": "GÜRAY VURAL",
                    "dakika": "26.dk",
                    "golTipi": "P"
                },
                {
                    "oyuncu": "HUGO RODALLEGA MARTINEZ",
                    "dakika": "44.dk",
                    "golTipi": "F"
                }
            ]
        }
    }
}